azure_ai_helper/__init__.py
azure_ai_helper/core.py
azure_ai_helper/language.py
azure_ai_helper/vision.py
azure_ai_helper-0.1.0.dist-info/METADATA
azure_ai_helper-0.1.0.dist-info/WHEEL
azure_ai_helper-0.1.0.dist-info/top_level.txt
azure_ai_helper-0.1.0.dist-info/RECORD
