Metadata-Version: 2.4
Name: azure-ai-helper
Version: 0.1.0
Summary: A simple, human-friendly wrapper over Azure AI Vision and Language services.
Author-email: Farhan ahmad <farhanbangash091@gmail.com>
Project-URL: Homepage, https://github.com/Farhanahmad-kust/AzureFramework
Project-URL: Repository, https://github.com/Farhanahmad-kust/AzureFramework
Keywords: azure,ai,vision,language,nlp,sdk,helper
Classifier: Programming Language :: Python :: 3
Classifier: Programming Language :: Python :: 3 :: Only
Classifier: Programming Language :: Python :: 3.9
Classifier: Programming Language :: Python :: 3.10
Classifier: Programming Language :: Python :: 3.11
Classifier: Intended Audience :: Developers
Classifier: Topic :: Software Development :: Libraries
Classifier: Environment :: Console
Requires-Python: >=3.9
Provides-Extra: vision
Requires-Dist: azure-cognitiveservices-vision-computervision>=0.9.0; extra == "vision"
Provides-Extra: language
Requires-Dist: azure-ai-textanalytics>=5.3.0; extra == "language"
Provides-Extra: all
Requires-Dist: azure-cognitiveservices-vision-computervision>=0.9.0; extra == "all"
Requires-Dist: azure-ai-textanalytics>=5.3.0; extra == "all"
